{
    "keep": {
        "days": false,
        "amount": 10
    },
    "auditLog": "logs\\.63fc75837471974c9a45d2e6dcda041852c0f58c-audit.json",
    "files": [
        {
            "date": 1609657468139,
            "name": "logs\\errorResult-2021-01-03.log",
            "hash": "523fab93361af480f9b50be09cf28d75"
        },
        {
            "date": 1609725697825,
            "name": "logs\\errorResult-2021-01-04.log",
            "hash": "06ac3980c887275012577b7f8e4aaacc"
        }
    ]
}